{"_id":{"$oid":"5ac57c64662b242d82fbbecd"},"creationDate":{"$date":"2018-04-05T01:31:16.464Z"},"media":{"$oid":"5ac57c38662b242d82fbbecb"},"status":"Private","owner":"5a997c0bcaa25766e4d42f1e","itemText":"sasasaszs","label":"zasasaaas","typeLabel":"Inventory item","type":"inventory","__v":0}
{"_id":{"$oid":"5accb308c12957674968b2f2"},"creationDate":{"$date":"2018-04-10T12:50:16.718Z"},"media":{"$oid":"5ac57c38662b242d82fbbecb"},"status":"Private","owner":"5a997c0bcaa25766e4d42f1e","itemText":"Bravo vous avez votre propre groupe","label":"Groupe de punk","typeLabel":"Inventory item","type":"inventory","__v":0}
